restful_dj/__init__.py
restful_dj/apis.py
restful_dj/decorator.py
restful_dj/meta.py
restful_dj/middleware.py
restful_dj/router.py
restful_dj/templates/restful_dj_api_list_template.html
restful_dj/util/__init__.py
restful_dj/util/collector.py
restful_dj/util/logger.py
restful_dj/util/utils.py
restful_dj-2.0.1.dist-info/LICENSE
restful_dj-2.0.1.dist-info/METADATA
restful_dj-2.0.1.dist-info/WHEEL
restful_dj-2.0.1.dist-info/top_level.txt
restful_dj-2.0.1.dist-info/RECORD
