Metadata-Version: 2.1
Name: restful-dj
Version: 2.0.1
Summary: restful(and auto route) support for Django2/3
Home-page: http://github.com/hyjiacan/restful-dj
Author: hyjiacan
Author-email: hyjiacan@163.com
License: MIT
Platform: UNKNOWN
Classifier: Programming Language :: Python :: 3
Classifier: License :: OSI Approved :: MIT License
Classifier: Operating System :: OS Independent
Classifier: Topic :: Internet :: WWW/HTTP :: Dynamic Content
Classifier: Topic :: Internet :: WWW/HTTP :: WSGI
Classifier: Topic :: Internet :: WWW/HTTP :: WSGI :: Application
Classifier: Topic :: Software Development :: Libraries :: Application Frameworks
Requires-Python: >=3.5
